MANIFEST.in
README.rst
VERSION
requirements.txt
setup.py
src/flask_graylog_bundle/__init__.py
src/flask_graylog_bundle/auth.py
src/flask_graylog_bundle/server.py
src/flask_graylog_bundle/validators.py
src/flask_graylog_bundle.egg-info/PKG-INFO
src/flask_graylog_bundle.egg-info/SOURCES.txt
src/flask_graylog_bundle.egg-info/dependency_links.txt
src/flask_graylog_bundle.egg-info/requires.txt
src/flask_graylog_bundle.egg-info/top_level.txt
src/flask_graylog_bundle.egg-info/zip-safe