Metadata-Version: 1.1
Name: flask-graylog-bundle
Version: 0.0.6
Summary: Flask Graylog client
Home-page: https://github.com/cdumay/flask-graylog-bundle
Author: Cedric DUMAY
Author-email: cedric.dumay@gmail.com
License: Apache License
Platform: UNKNOWN
Classifier: Programming Language :: Python
